badkeys/__init__.py
badkeys/checks.py
badkeys/dkim.py
badkeys/dnssec.py
badkeys/jwk.py
badkeys/runcli.py
badkeys/scanssh.py
badkeys/scantls.py
badkeys/update.py
badkeys/utils.py
badkeys/allkeys/__init__.py
badkeys/allkeys/block.py
badkeys/keydata/__init__.py
badkeys/keydata/primes1024.dat
badkeys/keydata/primes2048.dat
badkeys/keydata/primes4096.dat
badkeys/keydata/primes512.dat
badkeys/keydata/primes768.dat
badkeys/rsakeys/__init__.py
badkeys/rsakeys/fermat.py
badkeys/rsakeys/pattern.py
badkeys/rsakeys/roca.py
badkeys/rsakeys/rsainvalid.py
badkeys/rsakeys/rsawarnings.py
badkeys/rsakeys/sharedprimes.py
badkeys/rsakeys/smallfactors.py
badkeys/rsakeys/xzbackdoor.py
badkeys-0.0.15.dist-info/licenses/LICENSE
badkeys-0.0.15.dist-info/METADATA
badkeys-0.0.15.dist-info/WHEEL
badkeys-0.0.15.dist-info/entry_points.txt
badkeys-0.0.15.dist-info/top_level.txt
badkeys-0.0.15.dist-info/RECORD
