Metadata-Version: 2.4
Name: badkeys
Version: 0.0.15
Summary: Check cryptographic keys for known weaknesses
Author: Hanno Böck
License-Expression: MIT
Project-URL: Homepage, https://badkeys.info/
Project-URL: Source, https://github.com/badkeys/badkeys
Project-URL: Bug Tracker, https://github.com/badkeys/badkeys/issues
Keywords: security,cryptography,rsa
Classifier: Programming Language :: Python :: 3 :: Only
Classifier: Programming Language :: Python :: 3
Classifier: Programming Language :: Python :: 3.9
Classifier: Programming Language :: Python :: 3.10
Classifier: Programming Language :: Python :: 3.11
Classifier: Programming Language :: Python :: 3.12
Classifier: Programming Language :: Python :: 3.13
Classifier: Programming Language :: Python :: 3.14
Classifier: Natural Language :: English
Classifier: Development Status :: 4 - Beta
Requires-Python: >=3.9
License-File: LICENSE
Requires-Dist: gmpy2
Requires-Dist: cryptography
Provides-Extra: urllookup
Requires-Dist: binary-file-search; extra == "urllookup"
Provides-Extra: ssh
Requires-Dist: paramiko; extra == "ssh"
Provides-Extra: dkim
Requires-Dist: dnspython; extra == "dkim"
Dynamic: license-file
